gaodeweather_mcp_server/__init__.py
gaodeweather_mcp_server/server.py
gaodeweather_mcp_server-0.1.0.dist-info/METADATA
gaodeweather_mcp_server-0.1.0.dist-info/WHEEL
gaodeweather_mcp_server-0.1.0.dist-info/entry_points.txt
gaodeweather_mcp_server-0.1.0.dist-info/RECORD
